pypz/version.py
pypz/abstracts/__init__.py
pypz/abstracts/channel_ports.py
pypz/abstracts/misc.py
pypz/core/__init__.py
pypz/core/channels/__init__.py
pypz/core/channels/base.py
pypz/core/channels/io.py
pypz/core/channels/misc.py
pypz/core/channels/status.py
pypz/core/commons/__init__.py
pypz/core/commons/loggers.py
pypz/core/commons/parameters.py
pypz/core/commons/utils.py
pypz/core/specs/__init__.py
pypz/core/specs/dtos.py
pypz/core/specs/instance.py
pypz/core/specs/misc.py
pypz/core/specs/operator.py
pypz/core/specs/pipeline.py
pypz/core/specs/plugin.py
pypz/core/specs/utils.py
pypz/deployers/base.py
pypz/executors/__init__.py
pypz/executors/commons.py
pypz/executors/operator/__init__.py
pypz/executors/operator/context.py
pypz/executors/operator/executor.py
pypz/executors/operator/signals.py
pypz/executors/operator/states.py
pypz/executors/pipeline/__init__.py
pypz/executors/pipeline/executor.py
pypz/plugins/loggers/default.py
pypz/plugins/misc/health_check.py
pypz/runnables/__init__.py
pypz/runnables/operator.py
pypz_core-0.9.5.dist-info/licenses/LICENSE
pypz_core-0.9.5.dist-info/METADATA
pypz_core-0.9.5.dist-info/WHEEL
pypz_core-0.9.5.dist-info/top_level.txt
pypz_core-0.9.5.dist-info/RECORD
