Metadata-Version: 2.4
Name: pypz-core
Version: 0.9.5
Summary: Core components of pypz (pipes), which is a lightweight Pipeline as Code (PaC) framework.
Author-email: Laszlo Anka <laszlo.anka@gmail.com>
License: Apache-2.0
Project-URL: Documentation, https://pypz.dev
Project-URL: Repository, https://github.com/lazlowa/pypz-python
Keywords: pypz,pypz-core
Classifier: Natural Language :: English
Classifier: Operating System :: OS Independent
Classifier: Programming Language :: Python :: 3.11
Requires-Python: >=3.11
License-File: LICENSE
Requires-Dist: PyYAML~=6.0.1
Provides-Extra: static
Requires-Dist: flake8~=7.0.0; extra == "static"
Requires-Dist: flake8-html~=0.4.3; extra == "static"
Requires-Dist: mypy~=1.8.0; extra == "static"
Requires-Dist: coverage~=7.4.1; extra == "static"
Dynamic: license-file
